rosreestr_api/__init__.py
rosreestr_api/cacert.pem
rosreestr_api/clients/__init__.py
rosreestr_api/clients/http.py
rosreestr_api/clients/rosreestr.py
tests/__init__.py
tests/pkk_client_fixtures.py
tests/rosreestr_client_fixtures.py
tests/test_api_clients.py
rosreestr_api-1.0.0.dist-info/LICENCE.txt
rosreestr_api-1.0.0.dist-info/METADATA
rosreestr_api-1.0.0.dist-info/WHEEL
rosreestr_api-1.0.0.dist-info/top_level.txt
rosreestr_api-1.0.0.dist-info/RECORD
